lui_calculator/__init__.py
lui_calculator/complements.py
lui_calculator/core.py
lui_calculator/plot.py
lui_calculator/printer.py
lui_calculator/utils.py
lui_calculator-0.1.1.dist-info/LICENSE
lui_calculator-0.1.1.dist-info/METADATA
lui_calculator-0.1.1.dist-info/WHEEL
lui_calculator-0.1.1.dist-info/top_level.txt
lui_calculator-0.1.1.dist-info/RECORD
