Metadata-Version: 2.1
Name: lui-calculator
Version: 0.1.1
Summary: powerful calculator from strings with sympy
Author: NiniKo
License: MIT
Platform: unix
Platform: linux
Platform: osx
Platform: cygwin
Platform: win32
Classifier: Programming Language :: Python :: 3
Classifier: Programming Language :: Python :: 3 :: Only
Classifier: Programming Language :: Python :: 3.10
License-File: LICENSE
Requires-Dist: sympy (>=1.11)
Requires-Dist: requests (>=2.28)
Requires-Dist: types-requests (>=2.28)
Requires-Dist: numpy (>=1.23)
Requires-Dist: matplotlib (>=3.6)
Provides-Extra: testing
Requires-Dist: pytest (>=7.0) ; extra == 'testing'
Requires-Dist: pytest-cov (>=4.0) ; extra == 'testing'
Requires-Dist: mypy (>=0.982) ; extra == 'testing'
Requires-Dist: flake8 (>=5.0) ; extra == 'testing'
Requires-Dist: tox (>=3.27) ; extra == 'testing'
